README.md
setup.py
blwp/__init__.py
blwp/blwp_to_yml.py
blwp/prod.py
blwp/util.py
blwp/yml_to_blwp.py
blwpprod.egg-info/PKG-INFO
blwpprod.egg-info/SOURCES.txt
blwpprod.egg-info/dependency_links.txt
blwpprod.egg-info/entry_points.txt
blwpprod.egg-info/requires.txt
blwpprod.egg-info/top_level.txt